bidskit/__init__.py
bidskit/__main__.py
bidskit/bidsjson.py
bidskit/bidstree.py
bidskit/dcm2niix.py
bidskit/flywheel.py
bidskit/fmaps.py
bidskit/io.py
bidskit/templates/CHANGES
bidskit/templates/README
bidskit/templates/bidsignore
bidskit/templates/dataset_description.json
bidskit/templates/participants.json
bidskit/translate.py
bidskit-2025.11.7.dist-info/METADATA
bidskit-2025.11.7.dist-info/WHEEL
bidskit-2025.11.7.dist-info/entry_points.txt
bidskit-2025.11.7.dist-info/licenses/LICENSE.md
bidskit-2025.11.7.dist-info/RECORD
