Metadata-Version: 2.4
Name: bidskit
Version: 2025.11.7
Summary: BIDS curation toolkit
License: MIT
License-File: LICENSE.md
Author: Mike Tyszka
Author-email: jmt@caltech.edu
Requires-Python: >=3.10
Classifier: License :: OSI Approved :: MIT License
Classifier: Programming Language :: Python :: 3
Classifier: Programming Language :: Python :: 3.10
Classifier: Programming Language :: Python :: 3.11
Classifier: Programming Language :: Python :: 3.12
Classifier: Programming Language :: Python :: 3.13
Classifier: Programming Language :: Python :: 3.14
Requires-Dist: numpy (>=2.2.4)
Requires-Dist: pydicom (>=2.3.1,<2.4.0)
